HATmodels/PAiNN_adapted.py
HATmodels/__init__.py
kimmdy_hat/__init__.py
kimmdy_hat/cmd.py
kimmdy_hat/kimmdy-yaml-schema.json
kimmdy_hat/reaction.py
kimmdy_hat/save_predictions_only.py
kimmdy_hat/utils/__init__.py
kimmdy_hat/utils/capping_utils.py
kimmdy_hat/utils/input_generation.py
kimmdy_hat/utils/model_downloader.py
kimmdy_hat/utils/radical_creation_utils.py
kimmdy_hat/utils/trajectory_utils.py
kimmdy_hat/utils/utils.py
kimmdy_hat-1.2.0.dist-info/licenses/LICENSE
kimmdy_hat-1.2.0.dist-info/METADATA
kimmdy_hat-1.2.0.dist-info/WHEEL
kimmdy_hat-1.2.0.dist-info/entry_points.txt
kimmdy_hat-1.2.0.dist-info/top_level.txt
kimmdy_hat-1.2.0.dist-info/RECORD
